po/__init__.py
po/api/__init__.py
po/api/chat.py
po/api/file.py
po/core/WeChatType.py
po/core/__init__.py
po/lib/CONST.py
po/lib/__init__.py
po/lib/dec/__init__.py
po/lib/dec/act_dec.py
tests/__init__.py
tests/test.py
tests/test_file.py
powx-0.0.1.dist-info/LICENSE
powx-0.0.1.dist-info/METADATA
powx-0.0.1.dist-info/WHEEL
powx-0.0.1.dist-info/top_level.txt
powx-0.0.1.dist-info/RECORD
