Metadata-Version: 2.1
Name: powx
Version: 0.0.1
Summary: UNKNOWN
Home-page: http://python-office.com/
Author: CoderWanFeng
Author-email: 1957875073@qq.com
License: MIT
Project-URL: Bug Tracker, https://github.com/CoderWanFeng/python-office/issues
Project-URL: Documentation, https://github.com/CoderWanFeng/python-office/blob/master/README.md
Project-URL: Source Code, https://github.com/CoderWanFeng/python-office
Platform: any
Requires-Python: >=3.6
Requires-Dist: python-office
